{
    "cards": {
        "Visa_Classic_Debit": {
            "name": "Visa Classic Debit",
            "currency": ["KGS", "USD", "EUR"],
            "validity": "5 жыл",
            "issuance": "акысыз",
            "annual_fee": "акысыз",
            "descr": "Visa Classic картасы аркылуу кадимки төлөмдөрдөн тышкары контактсыз төлөмдөрдү жүргүзүү, интернет аркылуу төлөмдөрдү жасоо жана электрондук капчыктарды толуктоо мүмкүнчүлүктөрү камтылган. Каржылык эркиндикке жана өзгөчө стилге эшик ачыңыз. Биздин картабыз — бул жөн гана төлөм каражаты эмес, бул сиздин стилиңиздин жана ишенимиңиздин символу. DemirBankтын Visa International эл аралык төлөм системасынын карталары менен дүйнөнүн каалаган жеринде сатып алууларды жүргүзүү жана накталай акча алуу оңой жана ыңгайлуу! Негизги эсепти сом, доллар же евро менен тандоого болот.",
            "limits": {
                "contactless": {
                "transactions_count": "10 транзакция (ПИН-кодсуз)",
                "transactions_amount": "5 000 сом (ПИН-кодсуз)"
                },
                "atm_withdraw": {
                "kgs": "200 000 сом",
                "usd": "200 USD"
                },
                "internal_transfer_atm": "400 000 сом",
                "currency_exchange_atm": "50 000 сом",
                "pos_non_cash": "400 000 сом"
            }
        },
        "Visa_Gold_Debit": {
            "name": "Visa Gold Debit",
            "currency": ["KGS", "USD", "EUR"],
            "validity": "5 жыл",
            "issuance": "акысыз",
            "annual_fee": "1000 сом",
            "descr": "Бул карта PayWave технологиясы менен жабдылган. Анын жардамы менен соода түйүндөрүндө төлөмдөрдү картаңызды терминалга жакындатып, тез жана оңой түрдө төлөм жүргүзө аласыз. Visa Gold Debit картасынын универсалдуулугу: төлөмдөрдү контактсыз жүргүзүү мүмкүнчүлүгүн жана Gold деңгээлиндеги премиум кызматтарды бириктирет. DemirBankтын Visa International эл аралык төлөм системасынын карталары менен дүйнөнүн каалаган бурчунда сатып алууларды жүргүзүү жана накталай акча алуу өтө жеңил жана ыңгайлуу! Негизги эсепти сом же доллар менен ача аласыз.",
            "limits": {
                "contactless": {
                "transactions_count": "10 транзакция (ПИН-кодсуз)",
                "transactions_amount": "5 000 сом (ПИН-кодсуз)"
                },
                "atm_withdraw": {
                "kgs": "400 000 сом",
                "usd": "300 USD"
                },
                "internal_transfer_atm": "400 000 сом",
                "currency_exchange_atm": "50 000 сом",
                "pos_non_cash": "400 000 сом"
            }
        },
        "Visa_Platinum_Debit": {
            "name": "Visa Platinum Debit",
            "currency": ["KGS"],
            "validity": "5 жыл",
            "issuance": "акысыз",
            "annual_fee": "6000 сом",
            "descr": "Бул карта өз ээсинин өзгөчө статусун баса белгилөө үчүн атайын иштелип чыккан. Ал сизге максималдуу ыңгайлуулукту тартуулап, VIP-деңгээлдеги тейлөөнү камсыздайт жана дүйнөнүн каалаган жеринде эксклюзивдүү кызматтарды сунуштайт.Карта күнүмдүк турмушта да, сапар учурунда да жогорку деңгээлдеги ыңгайлуулукту берет.Негизги эсепти сом же доллар менен тандоого мүмкүнчүлүк бар.",
            "limits": {
                "contactless": {
                "transactions_count": "10 транзакция (ПИН-кодсуз)",
                "transactions_amount": "5 000 сом (ПИН-кодсуз)"
                },
                "atm_withdraw": {
                "kgs": "500 000 сом",
                "usd": "1000 USD"
                },
                "internal_transfer_atm": "400 000 сом",
                "currency_exchange_atm": "50 000 сом",
                "pos_non_cash": "1 000 000 сом"
            }
        },
        "Mastercard_Standard_Debit": {
            "name": "Mastercard Standard Debit",
            "currency": ["KGS", "USD", "EUR"],
            "validity": "5 жыл",
            "issuance": "акысыз",
            "annual_fee": "акысыз",
            "descr": "Mastercard Standard — бул дебеттик мультивалюталык карта. Ал кадимки контакттуу ыкма менен гана эмес, контактсыз (PayPass) төлөмдөрдү, интернет аркылуу сатып алууларды жана электрондук капчыктарды толтурууну да колдойт. Карта заманбап жана жарашыктуу дизайнга ээ.DemirBankтын Mastercard International эл аралык төлөм системасынын карталары менен дүйнөнүн каалаган бурчунда сатып алууларды жүргүзүү жана накталай акча алуу өтө жеңил жана ыңгайлуу!Негизги эсепти сом же евро менен ачууга болот.",
            "limits": {
                "contactless": {
                "transactions_count": "10 транзакция (ПИН-кодсуз)",
                "transactions_amount": "5 000 сом (ПИН-кодсуз)"
                },
                "atm_withdraw": {
                "kgs": "200 000 сом",
                "usd": "500 USD"
                },
                "internal_transfer_atm": "400 000 сом",
                "currency_exchange_atm": "50 000 сом",
                "pos_non_cash": "400 000 сом"
            }
        },
        "Mastercard_Gold_Debit": {
            "name": "Mastercard Gold Debit",
            "currency": ["KGS", "USD", "EUR"],
            "validity": "5 жыл",
            "issuance": "акысыз",
            "annual_fee": "1000 сом",
            "descr": "Бул карта PayPass технологиясы менен жабдылган. Бул технологиянын жардамы менен соода түйүндөрүндө контактсыз түрдө төлөм жүргүзүүгө болот.Mastercard Debit Gold – бул күнүмдүк төлөмдөр үчүн ыңгайлуулук жана премиалдык деңгээлдеги тейлөөнүн идеалдуу айкалышы менен контактсыз төлөм, жогорку комфорт жана 'Gold' классына татыктуу өзгөчө мүмкүнчүлүктөр – баары бир картанын ичинде.DemirBankтын Mastercard International эл аралык төлөм системасынын карталары менен дүйнөнүн каалаган бурчунда сатып алууларды жүргүзүү жана накталай акча алуу жеңил жана ыңгайлуу!Негизги эсепти сом же евро менен тандоого болот.",
            "limits": {
                "contactless": {
                "transactions_count": "10 транзакция (ПИН-кодсуз)",
                "transactions_amount": "5 000 сом (ПИН-кодсуз)"
                },
                "atm_withdraw": {
                "kgs": "400 000 сом",
                "usd": "300 USD"
                },
                "internal_transfer_atm": "400 000 сом",
                "currency_exchange_atm": "50 000 сом",
                "pos_non_cash": "400 000 сом"
            }
        },
        "Mastercard_Platinum_Debit": {
            "name": "Mastercard Platinum Debit",
            "currency": ["KGS", "USD", "EUR"],
            "validity": "5 жыл",
            "issuance": "акысыз",
            "annual_fee": "6000 сом",
            "descr": "Бул карта өз ээсинин өзгөчө статусун баса белгилөө үчүн атайын иштелип чыккан. Ал сизге максималдуу ыңгайлуулукту тартуулап, VIP-деңгээлдеги тейлөөнү камсыздайт жана дүйнөнүн каалаган жеринде эксклюзивдүү кызматтарды сунуштайт.Карта күнүмдүк турмушта да, сапар учурунда да жогорку деңгээлдеги ыңгайлуулукту берет.Негизги эсепти сом же евро менен тандоого мүмкүнчүлүк бар.",
            "limits": {
                "contactless": {
                "transactions_count": "10 транзакция (ПИН-кодсуз)",
                "transactions_amount": "5 000 сом (ПИН-кодсуз)"
                },
                "atm_withdraw": {
                "kgs": "500 000 сом",
                "usd": "1000 USD"
                },
                "internal_transfer_atm": "400 000 сом",
                "currency_exchange_atm": "50 000 сом",
                "pos_non_cash": "1 000 000 сом"
            }
        },
        "Visa_Classic_Credit": {
            "name": "Visa Classic Credit",
            "currency": ["KGS"],
            "validity": "5 жыл",
            "issuance": "акысыз",
            "annual_fee": "800 сом",
            "annual_fee_payroll_first_year": "акысыз",
            "annual_fee_payroll_next_years": "800 сом",
            "payroll_limit": "эмгек акыныӊ 70% чейин",
            "collateral": "Кредиттик лимит + 10% (эмгек акы долбоорунда жок)",
            "interest_rate_atm_cash": "30% жылдык",
            "interest_rate_pos": "0% айлык",
            "grace_period": "35 күнгө чейин",
            "additional_card": "Ооба",
            "descr": "Visa Classic эл аралык картасы — бул кеңири колдонулуучу банк картасы болуп эсептелет. Анын жардамы менен банк тарабынан белгиленген кредиттик лимиттин эсебинен ар кандай операцияларды жүргүзүүгө жана төлөмдөрдү аткарууга болот.Visa картасы менен каржыңызды ийкемдүү башкаруу мүмкүнчүлүгүнөн пайдаланыңыз. Дүкөндөрдө, ресторандарда жана онлайн — Visa карталары кабыл алынган бардык жерлерде төлөм жүргүзүңүз. Ийкемдүү кредиттик лимиттин шарттары менен күтүүсүз чыгымдар үчүн ар дайым кошумча каражаттарга ээ болосуз.",
            "limits": {
                "atm_withdraw": {
                    "kgs": "жеке лимитке жараша"
                },
                "payroll_limit": "эмгек акыныӊ 70% чейин"
            }
        },
        "Visa_Gold_Credit": {
            "name": "Visa Gold Credit",
            "currency": ["KGS"],
            "validity": "5 жыл",
            "issuance": "акысыз",
            "annual_fee": "1500 сом",
            "annual_fee_payroll_first_year": "акысыз",
            "annual_fee_payroll_next_years": "1500 сом",
            "payroll_limit": "эмгек акыныӊ 70% чейин",
            "collateral": "Кредиттик лимит + 10% (эмгек акы долбоорунда жок)",
            "interest_rate_atm_cash": "30% жылдык",
            "interest_rate_pos": "0% айлык",
            "grace_period": "35 күнгө чейин",
            "additional_card": "Ооба",
            "descr": "Visa Gold эл аралык картасы — бул сиздин каалаган учурда, каалаган жерде ишенимдүү жардамчыңыз!Алтын карта сиздин жогорку статусуңузду белгилеп, жөнөкөй карталардын ээлерине салыштырмлуу артыкчылыктарды тартуулайт: дүйнө жүзү боюнча арзандатуулар жана атайын сунуштар, артыкчылыктуу тейлөө жана жеке мамиле, ошондой эле сизди жана каражаттарыңызды коргоонун жогорку деңгээли.",
            "limits": {
                "atm_withdraw": {
                    "kgs": "жеке лимитке жараша"
                },
                "payroll_limit": "эмгек акыныӊ 70% чейин"
            }
        },
        "Visa_Platinum_Credit": {
            "name": "Visa Platinum Credit",
            "currency": ["KGS"],
            "validity": "5 жыл",
            "issuance": "акысыз",
            "annual_fee": "6000 сом",
            "annual_fee_payroll_first_year": "акысыз",
            "annual_fee_payroll_next_years": "6000 сом",
            "card_min_limit": "500 000 сом",
            "payroll_limit": "-",
            "collateral": "Кредиттик лимит + 10% (эмгек акы долбоорунда жок)",
            "interest_rate_atm_cash": "30% жылдык",
            "interest_rate_pos": "0% айлык",
            "grace_period": "35 күнгө чейин",
            "additional_card": "Ооба",
            "descr": "Visa Platinum кредиттик картасы — бул жөн гана төлөм каражаты эмес, бул сиздин премиалдык кызматтар жана артыкчылыктар дүйнөсүндөгү ишенимдүү жардамчыңыз. Эң көп баалаганыңыз – саякатпы, соода-сатыкпы же коопсуздукпу – биздин карта сиздин ишенимдүү өнөктөшүңүз болот."
        },
        "Mastercard_Standard_Credit": {
            "name": "Mastercard Standard Credit",
            "currency": ["KGS"],
            "validity": "5 жыл",
            "issuance": "акысыз",
            "annual_fee": "800 сом",
            "annual_fee_payroll_first_year": "акысыз",
            "annual_fee_payroll_next_years": "800 сом",
            "payroll_limit": "эмгек акыныӊ 70% чейин",
            "collateral": "Кредиттик лимит + 10% (эмгек акы долбоорунда жок)",
            "interest_rate_atm_cash": "30% жылдык",
            "interest_rate_pos": "0% айлык",
            "grace_period": "35 күнгө чейин",
            "additional_card": "Ооба",
            "descr": "Күнүмдүк сатып алуулардан тартып кыялданган саякатыңызга чейин, Mastercard Standard картасы – чыгымдарыңызды көзөмөлдөөгө жардам берген ыңгайлуу жана коопсуз инструмент."
        },
        "Mastercard_Gold_Credit": {
            "name": "Mastercard Gold Credit",
            "currency": ["KGS"],
            "validity": "5 жыл",
            "issuance": "акысыз",
            "annual_fee": "1500 сом",
            "annual_fee_payroll_first_year": "акысыз",
            "annual_fee_payroll_next_years": "1500 сом",
            "payroll_limit": "эмгек акыныӊ 70% чейин",
            "collateral": "Кредиттик лимит + 10% (эмгек акы долбоорунда жок)",
            "interest_rate_atm_cash": "30% жылдык",
            "interest_rate_pos": "0% айлык",
            "grace_period": "35 күнгө чейин",
            "additional_card": "Ооба",
            "descr": "Биз сизге жогорку каржылык статусуңузду белгилеген кеңейтилген кредиттик лимитти сунуштайбыз. Бул сизге чектөөсүз ири сатып алууларды, люкс саякаттарды жана чексиз ишкердик транзакцияларын ишке ашырууга мүмкүчүлүк берет."
        },
        "Mastercard_Platinum_Credit": {
            "name": "Mastercard Platinum Credit",
            "currency": ["KGS"],
            "validity": "5 жыл",
            "issuance": "акысыз",
            "annual_fee": "6000 сом",
            "annual_fee_payroll_first_year": "акысыз",
            "annual_fee_payroll_next_years": "6000 сом",
            "payroll_limit": "-",
            "collateral": "Кредиттик лимит + 10% (эмгек акы долбоорунда жок)",
            "interest_rate_atm_cash": "30% жылдык",
            "interest_rate_pos": "0% айлык",
            "grace_period": "35 күнгө чейин",
            "additional_card": "Ооба",
            "descr": "Дүйнө жүзү боюнча коопсуз жана ыңгайлуу төлөмдөр үчүн ишенимдүү тармак.Platinum пластик картасы менен сиз ар дайым жогорку деңгээлдеги кызматка жана Priority Pass кызматы аркылуу өзгөчө артыкчылыктарга ээ болосуз.Platinum картасынын ээси катары, сиз эс алуу менен сапардагы эң жогорку сапатты тандайсыз"
        },
        "Card_Plus": {
            "name": "Card Plus",
            "instructions": {
                "1": "Товарды тандаңыз. Баа + % сизге белгиленген лимиттен ашпашы керек.",
                "2": "Бөлүп төлөө мөнөтү. Сизге ыңгайлуу бөлүп төлөө мөөнөтүн тандайсыз.",
                "3": "Сатып алуу.Сатып алууну жыйынтыктаңыз! Төлөмдү ийгиликтүү өткөргөндөн кийин, төлөм графиги сизге дароо берилет!"
            },
            "rates": {
                "6": "9%",
                "9": "13.5%",
                "12": "18%"
            },
            "benefits": ["0%дан баштап", "Бөлүп төлөө мөөнөтүн өзүңүз тандайсыз (6, 9, 12 ай)", "500дөн ашык дүкөндөр, мейманканалар, мектептер, спорт залдар жана башка көптөгөн жайлар"],
            "descr": "'Card Plus' менен сатып алууларыңыздын акысын 6, 9 же 12 айга бөлүп төлөңүз. Азыр сатып алыңыз, кийин төлөңүз"
        },
        "virtual": {
          "name": "Virtual Card",
          "descr": "Виртуалдык карта – DemirBank кредиттик карталарынын ээлери үчүн интернет төлөмдөрүңүздүн коопсуздугун камсыз кылуу үчүн түзүлдү!Виртуалдык картаны – DemirBank online Интернет-банкинги же мобилдик тиркеме аркылуу өзүңүз түзөсүз. Карта физикалык түрдө чыгарылбайт, бул өз кезегинде карта уурдалып кетүү коркунучун жокко чыгарат.Виртуалдык картаны түзүү үчүн орнотулган лимити бар физикалык картанын болушу шарт.",
          "notes": ["Интернеттен сатып алуу жасап бүткөндөн кийин виртуалдык картанын лимитин азайтууга же нөлдөөгө мүмкүнчүлүк аласыз.", "Виртуалдык карта менен болгон бардык операциялар, банк тарабынан ай сайын электрондук почтага жөнөтүлгөн кредиттик карта боюнча эсеп-фактурада көрсөтүлөт."],
          "instructions": {
            "1": "Виртуалдык карта бир клик менен.Мобилдик тиркемеде",
            "2" : "Виртуалдык карта түзүү.Карта интернет-банкинг же мобилдик тиркеме аркылуу жеке бөлмөңүздө көрүнөт",
            "3" : "Лимит коюнуз.Сиздин виртуалдык картаңыз колдонууга даяр!"
          }
        },
        "elkart": {
            "name":"Elkart", 
            "descr": "Элкарт — бул Кыргыз Республикасынын аймагындагы банкоматтар аркылуу накталай эмес төлөмдөрдү жүргүзүүгө, айлык маяна, пенсия жана жөлөк пул алууга арналган карта.",
            "conditions": {
                "general": {
                    "issuance": "5000 сом",
                    "annual_fee": "100 сом"
                },
                "except": {
                    "name": "payroll project employees / employees of government institutions within payroll projects / pensioners",
                    "issuance": "акысыз",
                    "annual_fee": "акысыз"
                }
            }
        },
        "Visa_Campus_Card": {
            "name": "Visa Campus Card",
            "descr": "Кампус долбоору – бул ар бир билим берүү мекемеси же уюм үчүн ыңгайлуу жана заманбап чөйрө түзүүгө багытталган уникалдуу долбоор. Долбоордо турникеттерди, төлөм терминалдарын жана банкоматтарды бекер орнотуу жана тейлөө каралган. Бул долбоор билим берүү процесстерин жеңилдетип, студенттердин финансылык сабатуулугун жогорулатууга көмөктөшөт.Кампустук карта — универсалдуу чиптик карта, кампустук долбоордун ажырагыс бөлүгү болуп саналат. Ал банктын кызматтарын пайдаланууга мүмкүнчүлүк бергенден тышкары, студенттердин, мугалимдердин же кызматкерлердин өздүгүн тастыктоочу документ катары кызмат кылат.",
            "currency": ["KGS", "USD", "EUR"],
            "validity": "5 жыл",
            "limits": {
                "contactless": {
                "transactions_count": "10 транзакция (ПИН-кодсуз)",
                "transactions_amount": "5 000 сом (ПИН-кодсуз)"
                },
                "atm_withdraw": {
                "kgs": "200 000 сом",
                "usd": "200 USD"
                },
                "internal_transfer_atm": "400 000 сом",
                "currency_exchange_atm": "50 000 сом",
                "pos_non_cash": "400 000 сом"
            },
            "Services": ["Банктык кызматтар.төлөм картасынын бардык функциялары", "Интернет банкинг жана Мобилдик банкинг", "Мекеменин кызматтары үчүн төлөм жүргүзүү", "Электрондук өткөрмө. Ишке келип кетүү убактысын эсептөө", "Кирүү үчүн өткөрмө/ID карта.Мекеменин аймагындагы ДКИБтин өзгөчө турникеттери аркылуу кирүү үчүн", "Электрондук окуу билети"]
        }
    }
}